README.rst
setup.py
tta
tta/__init__.py
tta/__main__.py
tta/month_work.py
tta/tt_integration.py
tta/worked_days.py
tta.egg-info/PKG-INFO
tta.egg-info/SOURCES.txt
tta.egg-info/dependency_links.txt
tta.egg-info/entry_points.txt
tta.egg-info/not-zip-safe
tta.egg-info/requires.txt
tta.egg-info/top_level.txt