Metadata-Version: 1.1
Name: tta
Version: 0.2.0
Summary: Time Tracker Autocompleter for Muranosoft
Home-page: https://github.com/erm0l0v/tta
Author: Kirill Ermolov
Author-email: erm0l0v@ya.ru
License: UNKNOWN
Keywords: Time Tracker,Autocomplete,Muranosoft
Platform: UNKNOWN
Classifier: Development Status :: 2 - Pre-Alpha
Classifier: Programming Language :: Python
Classifier: Programming Language :: Python :: 2
Classifier: Programming Language :: Python :: 2.7
Classifier: Programming Language :: Python :: 3
Classifier: Programming Language :: Python :: 3.4
